wsdl
pyrannosaurus
