Metadata-Version: 1.0
Name: pyrannosaurus
Version: 0.0.5
Summary: Salesforce Development Tools
Home-page: https://github.com/kcshafer/pyrannosaurus/
Author: KC Shafer
Author-email: kclshafer@gmail.com
License: UNKNOWN
Keywords: salesforce
Platform: UNKNOWN
